p1/BlockChecker/BlockChecker.v
module BlockChecker(
    input clk,
    input reset,
    input [7:0] in,
    output reg result
);
reg [55:0] word;
reg [55:0] next_word;
reg [7:0] temp;
integer j = 0;
always @(*) begin
    if(in >= "A" && in <= "Z") begin
      temp = "a" + in - "A";
    end
    else begin
      temp = in;
    end
    next_word = (word << 8) + temp;
end
always @(posedge clk or posedge reset) begin
  if(reset == 1) begin
    word <= {48'b0," "};
    j <= 0;
    result <= 1;
  end
  else begin
    word <= next_word;

    if(next_word[39:0] == {"b","e","g","i","n"} && !(next_word[47:40] >= "a" && next_word[47:40] <= "z")) begin
      if(j>=0) begin
        j <= j + 1;
        result <= 0;
      end
    end
    else if(next_word [55:48] >= "a" && next_word[55:48] <= "z" && next_word[47:8] == {"b","e","g","i","n"})
      j <= j;
    else if(next_word[47:8] == {"b","e","g","i","n"} && next_word[7:0] >= "a" && next_word[7:0] <= "z") begin
      if(j>=0) begin
        j <= j - 1;
        result <= (j == 1) ? 1 : 0;
      end
    end
    else if(next_word[23:0] == {"e","n","d"} && !(next_word[31:24] >= "a" && next_word[31:24] <= "z")) begin
      j <= j - 1;
      result <= (j == 1) ? 1 : 0;
    end
    else if(next_word[39:32] >= "a" && next_word[39:32] <= "z" && next_word[31:8] == {"e","n","d"})
      j <= j;
    else if(next_word[31:8] == {"e","n","d"} && next_word[7:0] >= "a" && next_word[7:0] <= "z") begin
      j <= j + 1;
      result <= (j == -1) ? 1 : 0;
    end
  end
end
endmodule

p1/BlockChecker/BlockChecker_tb.v
`timescale  1ns / 1ps
`include "BlockChecker.v"
module tb_BlockChecker;

// BlockChecker Parameters
parameter PERIOD  = 10;


// BlockChecker Inputs
reg   clk                                  = 0 ;
reg   reset                                = 0 ;
reg   [7:0]  in                            = 0 ;

// BlockChecker Outputs
wire  result                               ;



BlockChecker  u_BlockChecker (
    .clk                     ( clk           ),
    .reset                   ( reset         ),
    .in                      ( in      [7:0] ),

    .result                  ( result        )
);
always #5 clk = ~clk;
initial
begin
    $dumpfile("test.vcd");
    $dumpvars;
    clk = 0;
    reset = 1;
    in = ",";
    #2
    reset = 0;
    #8
    in = "e";
    #10
    in = "n";
    #10
    in = "d";
    #10
    in = "d";
    #10
    in = "e";
    #10
    in = "n";
    #10
    in = "d";
    #10
    in = "s";
    #10
    in = " ";
    #10
    in = "B";
    #10
    in = "E";
    #10
    in = "g";
    #10
    in = "I";
    #10
    in = "n";
    #10
    in = ".";
    #10
    in = "B";
    #10
    in = "E";
    #10
    in = "g";
    #10
    in = "I";
    #10
    in = "n";
    #10
    in = ".";
    #10
    in = "E";
    #10
    in = "n";
    #10
    in = "d";
    #10
    in = ".";
    #10
    in = ",";
    #10
    in = "e";
    #10
    in = "n";
    #10
    in = "d";
    #10
    in = " ";
    #100
    $finish;
end

endmodule

p1/BlockChecker/test.vcd
$date
	Thu Oct 06 16:27:25 2022
$end
$version
	Icarus Verilog
$end
$timescale
	1ps
$end
$scope module tb_BlockChecker $end
$var wire 1 ! result $end
$var reg 1 " clk $end
$var reg 8 # in [7:0] $end
$var reg 1 $ reset $end
$scope module u_BlockChecker $end
$var wire 1 " clk $end
$var wire 8 % in [7:0] $end
$var wire 1 $ reset $end
$var reg 56 & next_word [55:0] $end
$var reg 1 ! result $end
$var reg 8 ' temp [7:0] $end
$var reg 56 ( word [55:0] $end
$var integer 32 ) j [31:0] $end
$upscope $end
$upscope $end
$enddefinitions $end
#0
$dumpvars
b0 )
b100000 (
b101100 '
b10000000101100 &
b101100 %
1$
b101100 #
0"
1!
$end
#2000
0$
#5000
b1000000010110000101100 &
b10000000101100 (
1"
#10000
b1000000010110001100101 &
b1100101 '
0"
b1100101 #
b1100101 %
#15000
b100000001011000110010101100101 &
b1000000010110001100101 (
1"
#20000
b100000001011000110010101101110 &
b1101110 '
0"
b1101110 #
b1101110 %
#25000
b10000000101100011001010110111001101110 &
b100000001011000110010101101110 (
1"
#30000
b10000000101100011001010110111001100100 &
b1100100 '
0"
b1100100 #
b1100100 %
#35000
b1000000010110001100101011011100110010001100100 &
0!
b11111111111111111111111111111111 )
b10000000101100011001010110111001100100 (
1"
#40000
0"
#45000
b100000001011000110010101101110011001000110010001100100 &
1!
b0 )
b1000000010110001100101011011100110010001100100 (
1"
#50000
b100000001011000110010101101110011001000110010001100101 &
b1100101 '
0"
b1100101 #
b1100101 %
#55000
b101100011001010110111001100100011001000110010101100101 &
b100000001011000110010101101110011001000110010001100101 (
1"
#60000
b101100011001010110111001100100011001000110010101101110 &
b1101110 '
0"
b1101110 #
b1101110 %
#65000
b1100101011011100110010001100100011001010110111001101110 &
b101100011001010110111001100100011001000110010101101110 (
1"
#70000
b1100101011011100110010001100100011001010110111001100100 &
b1100100 '
0"
b1100100 #
b1100100 %
#75000
b1101110011001000110010001100101011011100110010001100100 &
b1100101011011100110010001100100011001010110111001100100 (
1"
#80000
b1101110011001000110010001100101011011100110010001110011 &
b1110011 '
0"
b1110011 #
b1110011 %
#85000
b1100100011001000110010101101110011001000111001101110011 &
b1101110011001000110010001100101011011100110010001110011 (
1"
#90000
b1100100011001000110010101101110011001000111001100100000 &
b100000 '
0"
b100000 #
b100000 %
#95000
b1100100011001010110111001100100011100110010000000100000 &
b1100100011001000110010101101110011001000111001100100000 (
1"
#100000
b1100100011001010110111001100100011100110010000001100010 &
b1100010 '
0"
b1000010 #
b1000010 %
#105000
b1100101011011100110010001110011001000000110001001100010 &
b1100100011001010110111001100100011100110010000001100010 (
1"
#110000
b1100101011011100110010001110011001000000110001001100101 &
b1100101 '
0"
b1000101 #
b1000101 %
#115000
b1101110011001000111001100100000011000100110010101100101 &
b1100101011011100110010001110011001000000110001001100101 (
1"
#120000
b1101110011001000111001100100000011000100110010101100111 &
b1100111 '
0"
b1100111 #
b1100111 %
#125000
b1100100011100110010000001100010011001010110011101100111 &
b1101110011001000111001100100000011000100110010101100111 (
1"
#130000
b1100100011100110010000001100010011001010110011101101001 &
b1101001 '
0"
b1001001 #
b1001001 %
#135000
b1110011001000000110001001100101011001110110100101101001 &
b1100100011100110010000001100010011001010110011101101001 (
1"
#140000
b1110011001000000110001001100101011001110110100101101110 &
b1101110 '
0"
b1101110 #
b1101110 %
#145000
b100000011000100110010101100111011010010110111001101110 &
0!
b1 )
b1110011001000000110001001100101011001110110100101101110 (
1"
#150000
b100000011000100110010101100111011010010110111000101110 &
b101110 '
0"
b101110 #
b101110 %
#155000
b1100010011001010110011101101001011011100010111000101110 &
b100000011000100110010101100111011010010110111000101110 (
1"
#160000
b1100010011001010110011101101001011011100010111001100010 &
b1100010 '
0"
b1000010 #
b1000010 %
#165000
b1100101011001110110100101101110001011100110001001100010 &
b1100010011001010110011101101001011011100010111001100010 (
1"
#170000
b1100101011001110110100101101110001011100110001001100101 &
b1100101 '
0"
b1000101 #
b1000101 %
#175000
b1100111011010010110111000101110011000100110010101100101 &
b1100101011001110110100101101110001011100110001001100101 (
1"
#180000
b1100111011010010110111000101110011000100110010101100111 &
b1100111 '
0"
b1100111 #
b1100111 %
#185000
b1101001011011100010111001100010011001010110011101100111 &
b1100111011010010110111000101110011000100110010101100111 (
1"
#190000
b1101001011011100010111001100010011001010110011101101001 &
b1101001 '
0"
b1001001 #
b1001001 %
#195000
b1101110001011100110001001100101011001110110100101101001 &
b1101001011011100010111001100010011001010110011101101001 (
1"
#200000
b1101110001011100110001001100101011001110110100101101110 &
b1101110 '
0"
b1101110 #
b1101110 %
#205000
b101110011000100110010101100111011010010110111001101110 &
b10 )
b1101110001011100110001001100101011001110110100101101110 (
1"
#210000
b101110011000100110010101100111011010010110111000101110 &
b101110 '
0"
b101110 #
b101110 %
#215000
b1100010011001010110011101101001011011100010111000101110 &
b101110011000100110010101100111011010010110111000101110 (
1"
#220000
b1100010011001010110011101101001011011100010111001100101 &
b1100101 '
0"
b1000101 #
b1000101 %
#225000
b1100101011001110110100101101110001011100110010101100101 &
b1100010011001010110011101101001011011100010111001100101 (
1"
#230000
b1100101011001110110100101101110001011100110010101101110 &
b1101110 '
0"
b1101110 #
b1101110 %
#235000
b1100111011010010110111000101110011001010110111001101110 &
b1100101011001110110100101101110001011100110010101101110 (
1"
#240000
b1100111011010010110111000101110011001010110111001100100 &
b1100100 '
0"
b1100100 #
b1100100 %
#245000
b1101001011011100010111001100101011011100110010001100100 &
b1 )
b1100111011010010110111000101110011001010110111001100100 (
1"
#250000
b1101001011011100010111001100101011011100110010000101110 &
b101110 '
0"
b101110 #
b101110 %
#255000
b1101110001011100110010101101110011001000010111000101110 &
b1101001011011100010111001100101011011100110010000101110 (
1"
#260000
b1101110001011100110010101101110011001000010111000101100 &
b101100 '
0"
b101100 #
b101100 %
#265000
b101110011001010110111001100100001011100010110000101100 &
b1101110001011100110010101101110011001000010111000101100 (
1"
#270000
b101110011001010110111001100100001011100010110001100101 &
b1100101 '
0"
b1100101 #
b1100101 %
#275000
b1100101011011100110010000101110001011000110010101100101 &
b101110011001010110111001100100001011100010110001100101 (
1"
#280000
b1100101011011100110010000101110001011000110010101101110 &
b1101110 '
0"
b1101110 #
b1101110 %
#285000
b1101110011001000010111000101100011001010110111001101110 &
b1100101011011100110010000101110001011000110010101101110 (
1"
#290000
b1101110011001000010111000101100011001010110111001100100 &
b1100100 '
0"
b1100100 #
b1100100 %
#295000
b1100100001011100010110001100101011011100110010001100100 &
1!
b0 )
b1101110011001000010111000101100011001010110111001100100 (
1"
#300000
b1100100001011100010110001100101011011100110010000100000 &
b100000 '
0"
b100000 #
b100000 %
#305000
b101110001011000110010101101110011001000010000000100000 &
b1100100001011100010110001100101011011100110010000100000 (
1"
#310000
0"
#315000
b101100011001010110111001100100001000000010000000100000 &
b101110001011000110010101101110011001000010000000100000 (
1"
#320000
0"
#325000
b1100101011011100110010000100000001000000010000000100000 &
b101100011001010110111001100100001000000010000000100000 (
1"
#330000
0"
#335000
b1101110011001000010000000100000001000000010000000100000 &
b1100101011011100110010000100000001000000010000000100000 (
1"
#340000
0"
#345000
b1100100001000000010000000100000001000000010000000100000 &
b1101110011001000010000000100000001000000010000000100000 (
1"
#350000
0"
#355000
b100000001000000010000000100000001000000010000000100000 &
b1100100001000000010000000100000001000000010000000100000 (
1"
#360000
0"
#365000
b100000001000000010000000100000001000000010000000100000 (
1"
