p1/string2/string2.v
module string2(
    input clk,
    input clr,
    input [7:0] in,
    output out
);
localparam s0=0,s1=1,s2=2,s3=3,s4=4,s5=5,s6=6,s7=7;
reg [2:0] state,next_state;
initial begin
  state = s0;
  next_state = s0;
end
//状态转移，组合逻辑
always @(*) begin
    case(state)
      s0 : begin
        if(in >= "0" && in <= "9")
        next_state = s1;
        else if(in == "(")
        next_state = s3;
        else
        next_state = s7;
      end
      s1 : begin
        if(in == "+" || in == "*")
        next_state = s2;
        else
        next_state = s7;
      end
      s2 : begin
        if(in >= "0" && in <= "9")
        next_state = s1;
        else if(in == "(")
        next_state = s3;
        else
        next_state = s7;
      end
      s3 : begin
        if(in >= "0" && in <= "9")
        next_state = s4;
        else
        next_state = s7;
      end
      s4 : begin
        if(in == ")")
        next_state = s5;
        else if(in == "+" || in == "*")
        next_state = s6;
        else
        next_state = s7;
      end
      s5 : begin
        if(in == "+" || in == "*")
        next_state = s2;
        else
        next_state = s7;
      end
      s6 : begin
        if(in >= "0" && in <= "9")
        next_state = s4;
        else
        next_state = s7;
      end
      s7 : begin
        next_state = s7;
      end
      default : ;
    endcase
end
//状态储存,注意异步复位
always @(posedge clk, posedge clr) begin
  if(clr == 1)
  state <= s0;
  else
  state <= next_state;
end
//输出逻辑
assign out = (state == s1) ? 1 :
            (state == s5) ? 1 : 0;
endmodule

p1/string2/string2_tb.v
`timescale  1ns / 1ps
`include "string2.v"
module tb_string2;

// string2 Parameters
parameter PERIOD  = 10;


// string2 Inputs
reg   clk                                  = 0 ;
reg   clr                                  = 0 ;
reg   [7:0]  in                            = 0 ;

// string2 Outputs
wire  out                                  ;


string2  u_string2 (
    .clk                     ( clk        ),
    .clr                     ( clr        ),
    .in                      ( in   [7:0] ),

    .out                     ( out        )
);

always #5 clk = ~clk;
initial
begin
    $dumpfile("test.vcd");
    $dumpvars;
    clk = 0;
    clr = 0;
    in = "1";
    #2
    clr = 0;
    #8
    in = "+";
    #10
    in = "(";
    #10
    in = "1";
    #10
    in = "+";
    #10
    in = "2";
    #10
    in = "*";
    #10
    in = "1";
    #10
    in = "+";
    #10
    in = "2";
    #10
    in = ")";
    #10
    in = "*";
    #10
    in = "(";
    #10
    in = "3";
    #10
    in = ")";
    #10;
    $finish;
end

endmodule

p1/string2/test.vcd
$date
	Thu Oct 06 19:11:28 2022
$end
$version
	Icarus Verilog
$end
$timescale
	1ps
$end
$scope module tb_string2 $end
$var wire 1 ! out $end
$var reg 1 " clk $end
$var reg 1 # clr $end
$var reg 8 $ in [7:0] $end
$scope module u_string2 $end
$var wire 1 " clk $end
$var wire 1 # clr $end
$var wire 8 % in [7:0] $end
$var wire 1 ! out $end
$var reg 3 & next_state [2:0] $end
$var reg 3 ' state [2:0] $end
$upscope $end
$upscope $end
$enddefinitions $end
#0
$dumpvars
b0 '
b1 &
b110001 %
b110001 $
0#
0"
0!
$end
#5000
1!
b111 &
b1 '
1"
#10000
b10 &
0"
b101011 $
b101011 %
#15000
0!
b111 &
b10 '
1"
#20000
b11 &
0"
b101000 $
b101000 %
#25000
b111 &
b11 '
1"
#30000
b100 &
0"
b110001 $
b110001 %
#35000
b111 &
b100 '
1"
#40000
b110 &
0"
b101011 $
b101011 %
#45000
b111 &
b110 '
1"
#50000
b100 &
0"
b110010 $
b110010 %
#55000
b111 &
b100 '
1"
#60000
b110 &
0"
b101010 $
b101010 %
#65000
b111 &
b110 '
1"
#70000
b100 &
0"
b110001 $
b110001 %
#75000
b111 &
b100 '
1"
#80000
b110 &
0"
b101011 $
b101011 %
#85000
b111 &
b110 '
1"
#90000
b100 &
0"
b110010 $
b110010 %
#95000
b111 &
b100 '
1"
#100000
b101 &
0"
b101001 $
b101001 %
#105000
1!
b111 &
b101 '
1"
#110000
b10 &
0"
b101010 $
b101010 %
#115000
0!
b111 &
b10 '
1"
#120000
b11 &
0"
b101000 $
b101000 %
#125000
b111 &
b11 '
1"
#130000
b100 &
0"
b110011 $
b110011 %
#135000
b111 &
b100 '
1"
#140000
b101 &
0"
b101001 $
b101001 %
#145000
1!
b111 &
b101 '
1"
