Pre/Pre_Verilog/cpu_checker_challenge/define.v
`define s0 6'b000000//初始状态
`define s1 6'b000001      
`define s2 6'b000010
`define s3 6'b000011
`define s4 6'b000100
`define s5 6'b000101
`define s6 6'b000110
`define s7 6'b000111
`define s8 6'b001000
`define s9 6'b001001
`define s10 6'b001010
`define s11 6'b001011
`define s12 6'b001100
`define s13 6'b001101
`define s14 6'b001110
`define s15 6'b001111
`define s16 6'b010000
`define s17 6'b010001
`define s18 6'b010010
`define s19 6'b010011
`define s20 6'b010100
`define s21 6'b010101
`define s22 6'b010110
`define s23 6'b010111
`define s24 6'b011000
`define s25 6'b011001
`define s26 6'b011010
`define s27 6'b011011
`define s28 6'b011100
`define s29 6'b011101
`define s30 6'b011110
`define s31 6'b011111
`define s32 6'b100000
`define s33 6'b100001
`define s34 6'b100010
`define s35 6'b100011
`define s36 6'b100100
`define s37 6'b100101
`define s38 6'b100110
`define s39 6'b100111
`define s40 6'b101000
`define s41 6'b101001

Pre/Pre_Verilog/cpu_checker/cpu_checker.v
`include "define.v"
module cpu_checker(
    input clk,
    input reset,
    input [7:0] char,
    output reg [1:0] format_type
);
reg flag;
reg [5:0] state;
always @(posedge clk) begin
    if(reset == 1'b1) begin
      flag <= 1'b0;
      state <= `s0;
      format_type <= 2'b00;
    end
    else begin
      case(state)
      `s0 : begin
        format_type <= 2'b00;
        flag <= 1'b0;
        if(char == "^")
        state <= `s1;
        else
        state <= `s0;
      end
      `s1 : begin
        if(char == "^")
        state <= `s1;
        else if(char >= "0" && char <= "9")
        state <= `s2;
        else
        state <= `s0;
      end
      `s2 : begin
        if(char == "^")
        state <= `s1;
        else if(char >= "0" && char <= "9")
        state <= `s3;
        else if(char == "@")
        state <= `s6;
        else
        state <= `s0;
      end
      `s3 : begin
        if(char == "^")
        state <= `s1;
        else if(char == "@")
        state <= `s6;
        else if(char >= "0" && char <= "9")
        state <= `s4;
        else
        state <= `s0;
      end
      `s4 : begin
        if(char == "^")
        state <= `s1;
        else if(char == "@")
        state <= `s6;
        else if(char >= "0" && char <= "9")
        state <= `s5;
        else
        state <= `s0;
      end
      `s5 : begin
        if(char == "^")
        state <= `s1;
        else if(char == "@")
        state <= `s6;
        else
        state <= `s0;
      end
      `s6 : begin
        if(char == "^")
        state <= `s1;
        else if((char >= "0" && char <= "9")||(char >= "a" && char <= "f"))
        state <= `s7;
        else
        state <= `s0;
      end
      `s7 : begin
        if(char == "^")
        state <= `s1;
        else if((char >= "0" && char <= "9")||(char >= "a" && char <= "f"))
        state <= `s8;
        else
        state <= `s0;
      end
      `s8 : begin
        if(char == "^")
        state <= `s1;
        else if((char >= "0" && char <= "9")||(char >= "a" && char <= "f"))
        state <= `s9;
        else
        state <= `s0;        
      end
      `s9 : begin
        if(char == "^")
        state <= `s1;
        else if((char >= "0" && char <= "9")||(char >= "a" && char <= "f"))
        state <= `s10;
        else
        state <= `s0;        
      end
      `s10 : begin
        if(char == "^")
        state <= `s1;
        else if((char >= "0" && char <= "9")||(char >= "a" && char <= "f"))
        state <= `s11;
        else
        state <= `s0;         
      end
      `s11 : begin
        if(char == "^")
        state <= `s1;
        else if((char >= "0" && char <= "9")||(char >= "a" && char <= "f"))
        state <= `s12;
        else
        state <= `s0;          
      end
      `s12 : begin
        if(char == "^")
        state <= `s1;
        else if((char >= "0" && char <= "9")||(char >= "a" && char <= "f"))
        state <= `s13;
        else
        state <= `s0;
      end
      `s13 : begin
        if(char == "^")
        state <= `s1;
        else if((char >= "0" && char <= "9")||(char >= "a" && char <= "f"))
        state <= `s14;
        else
        state <= `s0;
      end
      `s14 : begin
        if(char == "^")
        state <= `s1;
        else if(char == ":")
        state <= `s15;
        else
        state <= `s0;
      end
      `s15 : begin
        if(char == "^")
        state <= `s1;
        else if(char == " ")
        state <= `s15;
        else if(char == "$") begin
          state <= `s16;
          flag <= 1'b0;
        end
        else if(char == "*") begin
          state <= `s33;
          flag <= 1'b1;
        end
        else
        state <= `s0;
      end
      `s16 : begin
        if(char == "^")
        state <= `s1;
        else if(char >= "0" && char <= "9")
        state <= `s17;
        else
        state <= `s0;
      end
      `s17 : begin
        if(char == "^")
        state <= `s1;
        else if(char >= "0" && char <= "9")
        state <= `s18;
        else if(char == " ")
        state <= `s21;
        else if(char == "<")
        state <= `s22;
        else
        state <= `s0;
      end
      `s18 : begin
        if(char == "^")
        state <= `s1;
        else if(char >= "0" && char <= "9")
        state <= `s19;
        else if(char == " ")
        state <= `s21;
        else if(char == "<")
        state <= `s22;
        else
        state <= `s0;        
      end
      `s19 : begin
        if(char == "^")
        state <= `s1;
        else if(char >= "0" && char <= "9")
        state <= `s20;
        else if(char == " ")
        state <= `s21;
        else if(char == "<")
        state <= `s22;
        else
        state <= `s0;
      end
      `s20 : begin
        if(char == "^")
        state <= `s1;
        else if(char == " ")
        state <= `s21;
        else if(char == "<")
        state <= `s22;
        else
        state <= `s0;
      end
      `s21 : begin
        if(char == "^")
        state <= `s1;
        else if(char == " ")
        state <= `s21;
        else if(char == "<")
        state <= `s22;
        else
        state <= `s0;
      end
      `s22 : begin
        if(char == "=")
        state <= `s23;
        else if(char == "^")
        state <= `s1;
        else
        state <= `s0;
      end
      `s23 : begin
        if(char == "^")
        state <= `s1;
        else if(char == " ")
        state <= `s23;
        else if((char >= "0" && char <= "9")||(char >= "a" && char <= "f"))
        state <= `s24;
        else
        state <= `s0;
      end
      `s24 : begin
        if(char == "^")
        state <= `s1;
        else if((char >= "0" && char <= "9")||(char >= "a" && char <= "f"))
        state <= `s25;
        else
        state <= `s0;        
      end
      `s25 : begin
        if(char == "^")
        state <= `s1;
        else if((char >= "0" && char <= "9")||(char >= "a" && char <= "f"))
        state <= `s26;
        else
        state <= `s0;         
      end
      `s26 : begin
        if(char == "^")
        state <= `s1;
        else if((char >= "0" && char <= "9")||(char >= "a" && char <= "f"))
        state <= `s27;
        else
        state <= `s0; 
      end
      `s27 : begin
        if(char == "^")
        state <= `s1;
        else if((char >= "0" && char <= "9")||(char >= "a" && char <= "f"))
        state <= `s28;
        else
        state <= `s0; 
      end
      `s28 : begin
        if(char == "^")
        state <= `s1;
        else if((char >= "0" && char <= "9")||(char >= "a" && char <= "f"))
        state <= `s29;
        else
        state <= `s0; 
      end
      `s29 : begin
        if(char == "^")
        state <= `s1;
        else if((char >= "0" && char <= "9")||(char >= "a" && char <= "f"))
        state <= `s30;
        else
        state <= `s0; 
      end
      `s30 : begin
        if(char == "^")
        state <= `s1;
        else if((char >= "0" && char <= "9")||(char >= "a" && char <= "f"))
        state <= `s31;
        else
        state <= `s0; 
      end
      `s31 : begin
        if(char == "^")
        state <= `s1;
        else if(char == "#") begin
          state <= `s0;
          if(flag == 1'b0)
          format_type <= 2'b01;
          else
          format_type <= 2'b10;
        end
        else
        state <= `s0;
      end
      `s33 : begin
        if(char == "^")
        state <= `s1;
        else if((char >= "0" && char <= "9")||(char >= "a" && char <= "f"))
        state <= `s34;
        else
        state <= `s0;
      end
      `s34 : begin
        if(char == "^")
        state <= `s1;
        else if((char >= "0" && char <= "9")||(char >= "a" && char <= "f"))
        state <= `s35;
        else
        state <= `s0;        
      end
      `s35 : begin
        if(char == "^")
        state <= `s1;
        else if((char >= "0" && char <= "9")||(char >= "a" && char <= "f"))
        state <= `s36;
        else
        state <= `s0;
      end
      `s36 : begin
        if(char == "^")
        state <= `s1;
        else if((char >= "0" && char <= "9")||(char >= "a" && char <= "f"))
        state <= `s37;
        else
        state <= `s0;
      end
      `s37 : begin
        if(char == "^")
        state <= `s1;
        else if((char >= "0" && char <= "9")||(char >= "a" && char <= "f"))
        state <= `s38;
        else
        state <= `s0;
      end
      `s38 : begin
        if(char == "^")
        state <= `s1;
        else if((char >= "0" && char <= "9")||(char >= "a" && char <= "f"))
        state <= `s39;
        else
        state <= `s0;
      end
      `s39 : begin
        if(char == "^")
        state <= `s1;
        else if((char >= "0" && char <= "9")||(char >= "a" && char <= "f"))
        state <= `s40;
        else
        state <= `s0;
      end
      `s40 : begin
        if(char == "^")
        state <= `s1;
        else if((char >= "0" && char <= "9")||(char >= "a" && char <= "f"))
        state <= `s41;
        else
        state <= `s0;
      end
      `s41 : begin
        if(char == "^")
        state <= `s1;
        else if(char == " ")
        state <= `s21;
        else if(char == "<")
        state <= `s22;
      end
      endcase
    end
end
endmodule

Pre/Pre_Verilog/cpu_checker/cpu_checker_tb.v
`timescale  1ns / 1ps
`include "cpu_checker.v"
module tb_cpu_checker;

// cpu_checker Parameters
parameter PERIOD  = 10;


// cpu_checker Inputs
reg   clk                                  = 0 ;
reg   reset                                = 0 ;
reg   [7:0]  char                          = 0 ;
reg [15:0] freq;
reg finish;
// cpu_checker Outputs
wire  [1:0]  format_type                   ;
wire [3:0] error_code;

   always @(posedge clk) begin
      if (!reset && !finish) begin
         $display("%d", format_type);
      end
   end

cpu_checker  u_cpu_checker (
    .clk                     ( clk                ),
    .reset                   ( reset              ),
    .char                    ( char         [7:0] ),

    .format_type             ( format_type  [1:0] )
);

initial
begin
    $dumpfile("cpu_checker.vcd");
    $dumpvars;
		clk = 0;
		reset = 1;
		char = 0;
		freq = 2;
		finish = 0;

		#10 reset = 0;
		#2 char = "^";
#2 char = "2";
#2 char = "4";
#2 char = "2";
#2 char = "@";
#2 char = "0";
#2 char = "0";
#2 char = "0";
#2 char = "0";
#2 char = "3";
#2 char = "0";
#2 char = "f";
#2 char = "4";
#2 char = ":";
#2 char = " ";
#2 char = "$";
#2 char = "3";
#2 char = "1";
#2 char = " ";
#2 char = "<";
#2 char = "=";
#2 char = "1";
#2 char = "2";
#2 char = "3";
#2 char = "4";
#2 char = "5";
#2 char = "6";
#2 char = "7";
#2 char = "8";
#2 char = "#";
#2 char = "^";
#2 char = "2";
#2 char = "4";
#2 char = "2";
#2 char = "@";
#2 char = "0";
#2 char = "0";
#2 char = "0";
#2 char = "0";
#2 char = "3";
#2 char = "0";
#2 char = "f";
#2 char = "4";
#2 char = ":";
#2 char = " ";
#2 char = "$";
#2 char = "3";
#2 char = "1";
#2 char = " ";
#2 char = "<";
#2 char = "=";
#2 char = "1";
#2 char = "2";
#2 char = "3";
#2 char = "2";
#2 char = "1";
#2 char = "5";
#2 char = "#";
#2 char = "^";
#2 char = "2";
#2 char = "4";
#2 char = "2";
#2 char = "@";
#2 char = "0";
#2 char = "0";
#2 char = "0";
#2 char = "0";
#2 char = "3";
#2 char = "0";
#2 char = "f";
#2 char = "4";
#2 char = ":";
#2 char = " ";
#2 char = "$";
#2 char = "3";
#2 char = "1";
#2 char = " ";
#2 char = "<";
#2 char = "=";
#2 char = "1";
#2 char = "2";
#2 char = "3";
#2 char = "2";
#2 char = "1";
#2 char = "5";
#2 char = "8";
#2 char = "9";
#2 char = "9";
#2 char = "8";
#2 char = "#";
#2 char = "^";
#2 char = "2";
#2 char = "4";
#2 char = "2";
#2 char = "@";
#2 char = "0";
#2 char = "0";
#2 char = "0";
#2 char = "0";
#2 char = "3";
#2 char = "0";
#2 char = "f";
#2 char = "4";
#2 char = ":";
#2 char = " ";
#2 char = "$";
#2 char = "3";
#2 char = "1";
#2 char = " ";
#2 char = "<";
#2 char = "=";
#2 char = "#";
#2 char = "^";
#2 char = "2";
#2 char = "4";
#2 char = "2";
#2 char = "@";
#2 char = "0";
#2 char = "0";
#2 char = "0";
#2 char = "0";
#2 char = "3";
#2 char = "0";
#2 char = "f";
#2 char = "4";
#2 char = ":";
#2 char = " ";
#2 char = "$";
#2 char = "3";
#2 char = "1";
#2 char = " ";
#2 char = "<";
#2 char = "=";
#2 char = " ";
#2 char = " ";
#2 char = " ";
#2 char = "1";
#2 char = "2";
#2 char = "3";
#2 char = "2";
#2 char = "1";
#2 char = "5";
#2 char = " ";
#2 char = "#";
#2 char = "^";
#2 char = "2";
#2 char = "4";
#2 char = "2";
#2 char = "@";
#2 char = "0";
#2 char = "0";
#2 char = "0";
#2 char = "0";
#2 char = "3";
#2 char = "0";
#2 char = "f";
#2 char = "4";
#2 char = ":";
#2 char = " ";
#2 char = "$";
#2 char = "3";
#2 char = "1";
#2 char = " ";
#2 char = "<";
#2 char = "=";
#2 char = " ";
#2 char = " ";
#2 char = " ";
#2 char = "a";
#2 char = "b";
#2 char = "1";
#2 char = "2";
#2 char = "3";
#2 char = "2";
#2 char = "1";
#2 char = "5";
#2 char = " ";
#2 char = "#";
#2 char = "^";
#2 char = "2";
#2 char = "4";
#2 char = "2";
#2 char = "@";
#2 char = "0";
#2 char = "0";
#2 char = "0";
#2 char = "0";
#2 char = "3";
#2 char = "0";
#2 char = "f";
#2 char = "4";
#2 char = ":";
#2 char = " ";
#2 char = "$";
#2 char = "3";
#2 char = "1";
#2 char = " ";
#2 char = "<";
#2 char = "=";
#2 char = " ";
#2 char = " ";
#2 char = " ";
#2 char = "A";
#2 char = "b";
#2 char = "1";
#2 char = "2";
#2 char = "3";
#2 char = "2";
#2 char = "1";
#2 char = "5";
#2 char = " ";
#2 char = "#";
#2 char = "^";
#2 char = "3";
#2 char = "3";
#2 char = "8";
#2 char = "@";
#2 char = "0";
#2 char = "0";
#2 char = "0";
#2 char = "0";
#2 char = "3";
#2 char = "1";
#2 char = "3";
#2 char = "0";
#2 char = ":";
#2 char = " ";
#2 char = "*";
#2 char = "0";
#2 char = "0";
#2 char = "0";
#2 char = "0";
#2 char = "0";
#2 char = "0";
#2 char = "8";
#2 char = "8";
#2 char = " ";
#2 char = "<";
#2 char = "=";
#2 char = " ";
#2 char = "F";
#2 char = "f";
#2 char = "f";
#2 char = "f";
#2 char = "b";
#2 char = "5";
#2 char = "2";
#2 char = "8";
#2 char = "#";
#2 char = "^";
#2 char = "3";
#2 char = "3";
#2 char = "8";
#2 char = "@";
#2 char = "0";
#2 char = "0";
#2 char = "0";
#2 char = "0";
#2 char = "3";
#2 char = "1";
#2 char = "3";
#2 char = "0";
#2 char = ":";
#2 char = " ";
#2 char = "*";
#2 char = "0";
#2 char = "0";
#2 char = "0";
#2 char = "0";
#2 char = "0";
#2 char = "0";
#2 char = "8";
#2 char = "8";
#2 char = " ";
#2 char = "<";
#2 char = "=";
#2 char = " ";
#2 char = "f";
#2 char = "f";
#2 char = "f";
#2 char = "f";
#2 char = "b";
#2 char = "5";
#2 char = "2";
#2 char = "8";
#2 char = "#";
#2 char = "^";
#2 char = "3";
#2 char = "3";
#2 char = "8";
#2 char = "@";
#2 char = "0";
#2 char = "0";
#2 char = "0";
#2 char = "0";
#2 char = "3";
#2 char = "1";
#2 char = "3";
#2 char = "0";
#2 char = ":";
#2 char = " ";
#2 char = "*";
#2 char = "0";
#2 char = "0";
#2 char = "0";
#2 char = "0";
#2 char = "0";
#2 char = "0";
#2 char = "8";
#2 char = "8";
#2 char = " ";
#2 char = "<";
#2 char = "=";
#2 char = "#";
#2 char = "^";
#2 char = "3";
#2 char = "3";
#2 char = "8";
#2 char = "@";
#2 char = "0";
#2 char = "0";
#2 char = "0";
#2 char = "0";
#2 char = "3";
#2 char = "1";
#2 char = "3";
#2 char = "0";
#2 char = ":";
#2 char = " ";
#2 char = "*";
#2 char = "0";
#2 char = "0";
#2 char = "0";
#2 char = "0";
#2 char = "0";
#2 char = "0";
#2 char = "8";
#2 char = "8";
#2 char = " ";
#2 char = "<";
#2 char = "=";
#2 char = " ";
#2 char = "f";
#2 char = "f";
#2 char = "f";
#2 char = "f";
#2 char = "b";
#2 char = "5";
#2 char = "2";
#2 char = "8";
#2 char = "1";
#2 char = "2";
#2 char = "#";
#2 char = "^";
#2 char = "3";
#2 char = "3";
#2 char = "8";
#2 char = "@";
#2 char = "0";
#2 char = "0";
#2 char = "0";
#2 char = "0";
#2 char = "3";
#2 char = "1";
#2 char = "3";
#2 char = "0";
#2 char = ":";
#2 char = " ";
#2 char = "*";
#2 char = "0";
#2 char = "0";
#2 char = "0";
#2 char = "0";
#2 char = "0";
#2 char = "0";
#2 char = "8";
#2 char = "8";
#2 char = " ";
#2 char = "<";
#2 char = "=";
#2 char = " ";
#2 char = "f";
#2 char = "f";
#2 char = "f";
#2 char = "f";
#2 char = "b";
#2 char = "5";
#2 char = "2";
#2 char = "#";
#2 char = "^";
#2 char = "3";
#2 char = "3";
#2 char = "8";
#2 char = "@";
#2 char = "0";
#2 char = "0";
#2 char = "0";
#2 char = "0";
#2 char = "3";
#2 char = "1";
#2 char = "3";
#2 char = "0";
#2 char = ":";
#2 char = " ";
#2 char = "*";
#2 char = "0";
#2 char = "0";
#2 char = "0";
#2 char = "0";
#2 char = "0";
#2 char = "0";
#2 char = "8";
#2 char = "8";
#2 char = " ";
#2 char = "<";
#2 char = "=";
#2 char = " ";
#2 char = "f";
#2 char = "f";
#2 char = "f";
#2 char = "f";
#2 char = "B";
#2 char = "5";
#2 char = "2";
#2 char = "8";
#2 char = "#";
#2 char = "^";
#2 char = "3";
#2 char = "3";
#2 char = "8";
#2 char = "@";
#2 char = "0";
#2 char = "0";
#2 char = "0";
#2 char = "0";
#2 char = "3";
#2 char = "1";
#2 char = "3";
#2 char = "0";
#2 char = ":";
#2 char = " ";
#2 char = "*";
#2 char = "0";
#2 char = "0";
#2 char = "0";
#2 char = "0";
#2 char = "0";
#2 char = "0";
#2 char = "8";
#2 char = "8";
#2 char = " ";
#2 char = "<";
#2 char = "=";
#2 char = " ";
#2 char = "f";
#2 char = "f";
#2 char = "f";
#2 char = "f";
#2 char = "b";
#2 char = "5";
#2 char = "2";
#2 char = "B";
#2 char = "#";
#2 char = "^";
#2 char = "3";
#2 char = "3";
#2 char = "8";
#2 char = "@";
#2 char = "0";
#2 char = "0";
#2 char = "0";
#2 char = "0";
#2 char = "3";
#2 char = "1";
#2 char = "3";
#2 char = "0";
#2 char = ":";
#2 char = " ";
#2 char = "*";
#2 char = "0";
#2 char = "0";
#2 char = "0";
#2 char = "0";
#2 char = "0";
#2 char = "0";
#2 char = "8";
#2 char = "8";
#2 char = " ";
#2 char = "<";
#2 char = "=";
#2 char = " ";
#2 char = "f";
#2 char = "f";
#2 char = "f";
#2 char = "f";
#2 char = "b";
#2 char = "5";
#2 char = "2";
#2 char = "B";
#2 char = "#";
#2 char = "^";
#2 char = "3";
#2 char = "3";
#2 char = "8";
#2 char = "@";
#2 char = "0";
#2 char = "0";
#2 char = "0";
#2 char = "0";
#2 char = "3";
#2 char = "1";
#2 char = "3";
#2 char = "0";
#2 char = ":";
#2 char = " ";
#2 char = "*";
#2 char = "0";
#2 char = "0";
#2 char = "0";
#2 char = "0";
#2 char = "0";
#2 char = "0";
#2 char = "8";
#2 char = "8";
#2 char = " ";
#2 char = "<";
#2 char = "=";
#2 char = " ";
#2 char = "f";
#2 char = "f";
#2 char = "f";
#2 char = "f";
#2 char = "b";
#2 char = "5";
#2 char = "2";
#2 char = "B";
#2 char = " ";
#2 char = "#";
		#20
		finish = 1;
    $finish;
end
    always #1 clk = ~clk;

endmodule

Pre/Pre_Verilog/cpu_checker/cpu_checker.vcd
$date
	Thu Sep 08 20:34:03 2022
$end
$version
	Icarus Verilog
$end
$timescale
	1ps
$end
$scope module tb_cpu_checker $end
$var wire 2 ! format_type [1:0] $end
$var reg 8 " char [7:0] $end
$var reg 1 # clk $end
$var reg 1 $ finish $end
$var reg 16 % freq [15:0] $end
$var reg 1 & reset $end
$scope module u_cpu_checker $end
$var wire 8 ' char [7:0] $end
$var wire 1 # clk $end
$var wire 1 & reset $end
$var reg 1 ( flag $end
$var reg 2 ) format_type [1:0] $end
$var reg 6 * state [5:0] $end
$upscope $end
$upscope $end
$enddefinitions $end
#0
$dumpvars
bx *
bx )
x(
b0 '
1&
b10 %
0$
0#
b0 "
bx !
$end
#1000
b0 !
b0 )
b0 *
0(
1#
#2000
0#
#3000
1#
#4000
0#
#5000
1#
#6000
0#
#7000
1#
#8000
0#
#9000
1#
#10000
0#
0&
#11000
1#
#12000
0#
b1011110 "
b1011110 '
#13000
b1 *
1#
#14000
0#
b110010 "
b110010 '
#15000
b10 *
1#
#16000
0#
b110100 "
b110100 '
#17000
b11 *
1#
#18000
0#
b110010 "
b110010 '
#19000
b100 *
1#
#20000
0#
b1000000 "
b1000000 '
#21000
b110 *
1#
#22000
0#
b110000 "
b110000 '
#23000
b111 *
1#
#24000
0#
#25000
b1000 *
1#
#26000
0#
#27000
b1001 *
1#
#28000
0#
#29000
b1010 *
1#
#30000
0#
b110011 "
b110011 '
#31000
b1011 *
1#
#32000
0#
b110000 "
b110000 '
#33000
b1100 *
1#
#34000
0#
b1100110 "
b1100110 '
#35000
b1101 *
1#
#36000
0#
b110100 "
b110100 '
#37000
b1110 *
1#
#38000
0#
b111010 "
b111010 '
#39000
b1111 *
1#
#40000
0#
b100000 "
b100000 '
#41000
1#
#42000
0#
b100100 "
b100100 '
#43000
b10000 *
1#
#44000
0#
b110011 "
b110011 '
#45000
b10001 *
1#
#46000
0#
b110001 "
b110001 '
#47000
b10010 *
1#
#48000
0#
b100000 "
b100000 '
#49000
b10101 *
1#
#50000
0#
b111100 "
b111100 '
#51000
b10110 *
1#
#52000
0#
b111101 "
b111101 '
#53000
b10111 *
1#
#54000
0#
b110001 "
b110001 '
#55000
b11000 *
1#
#56000
0#
b110010 "
b110010 '
#57000
b11001 *
1#
#58000
0#
b110011 "
b110011 '
#59000
b11010 *
1#
#60000
0#
b110100 "
b110100 '
#61000
b11011 *
1#
#62000
0#
b110101 "
b110101 '
#63000
b11100 *
1#
#64000
0#
b110110 "
b110110 '
#65000
b11101 *
1#
#66000
0#
b110111 "
b110111 '
#67000
b11110 *
1#
#68000
0#
b111000 "
b111000 '
#69000
b11111 *
1#
#70000
0#
b100011 "
b100011 '
#71000
b1 !
b1 )
b0 *
1#
#72000
0#
b1011110 "
b1011110 '
#73000
b1 *
b0 !
b0 )
1#
#74000
0#
b110010 "
b110010 '
#75000
b10 *
1#
#76000
0#
b110100 "
b110100 '
#77000
b11 *
1#
#78000
0#
b110010 "
b110010 '
#79000
b100 *
1#
#80000
0#
b1000000 "
b1000000 '
#81000
b110 *
1#
#82000
0#
b110000 "
b110000 '
#83000
b111 *
1#
#84000
0#
#85000
b1000 *
1#
#86000
0#
#87000
b1001 *
1#
#88000
0#
#89000
b1010 *
1#
#90000
0#
b110011 "
b110011 '
#91000
b1011 *
1#
#92000
0#
b110000 "
b110000 '
#93000
b1100 *
1#
#94000
0#
b1100110 "
b1100110 '
#95000
b1101 *
1#
#96000
0#
b110100 "
b110100 '
#97000
b1110 *
1#
#98000
0#
b111010 "
b111010 '
#99000
b1111 *
1#
#100000
0#
b100000 "
b100000 '
#101000
1#
#102000
0#
b100100 "
b100100 '
#103000
b10000 *
1#
#104000
0#
b110011 "
b110011 '
#105000
b10001 *
1#
#106000
0#
b110001 "
b110001 '
#107000
b10010 *
1#
#108000
0#
b100000 "
b100000 '
#109000
b10101 *
1#
#110000
0#
b111100 "
b111100 '
#111000
b10110 *
1#
#112000
0#
b111101 "
b111101 '
#113000
b10111 *
1#
#114000
0#
b110001 "
b110001 '
#115000
b11000 *
1#
#116000
0#
b110010 "
b110010 '
#117000
b11001 *
1#
#118000
0#
b110011 "
b110011 '
#119000
b11010 *
1#
#120000
0#
b110010 "
b110010 '
#121000
b11011 *
1#
#122000
0#
b110001 "
b110001 '
#123000
b11100 *
1#
#124000
0#
b110101 "
b110101 '
#125000
b11101 *
1#
#126000
0#
b100011 "
b100011 '
#127000
b0 *
1#
#128000
0#
b1011110 "
b1011110 '
#129000
b1 *
1#
#130000
0#
b110010 "
b110010 '
#131000
b10 *
1#
#132000
0#
b110100 "
b110100 '
#133000
b11 *
1#
#134000
0#
b110010 "
b110010 '
#135000
b100 *
1#
#136000
0#
b1000000 "
b1000000 '
#137000
b110 *
1#
#138000
0#
b110000 "
b110000 '
#139000
b111 *
1#
#140000
0#
#141000
b1000 *
1#
#142000
0#
#143000
b1001 *
1#
#144000
0#
#145000
b1010 *
1#
#146000
0#
b110011 "
b110011 '
#147000
b1011 *
1#
#148000
0#
b110000 "
b110000 '
#149000
b1100 *
1#
#150000
0#
b1100110 "
b1100110 '
#151000
b1101 *
1#
#152000
0#
b110100 "
b110100 '
#153000
b1110 *
1#
#154000
0#
b111010 "
b111010 '
#155000
b1111 *
1#
#156000
0#
b100000 "
b100000 '
#157000
1#
#158000
0#
b100100 "
b100100 '
#159000
b10000 *
1#
#160000
0#
b110011 "
b110011 '
#161000
b10001 *
1#
#162000
0#
b110001 "
b110001 '
#163000
b10010 *
1#
#164000
0#
b100000 "
b100000 '
#165000
b10101 *
1#
#166000
0#
b111100 "
b111100 '
#167000
b10110 *
1#
#168000
0#
b111101 "
b111101 '
#169000
b10111 *
1#
#170000
0#
b110001 "
b110001 '
#171000
b11000 *
1#
#172000
0#
b110010 "
b110010 '
#173000
b11001 *
1#
#174000
0#
b110011 "
b110011 '
#175000
b11010 *
1#
#176000
0#
b110010 "
b110010 '
#177000
b11011 *
1#
#178000
0#
b110001 "
b110001 '
#179000
b11100 *
1#
#180000
0#
b110101 "
b110101 '
#181000
b11101 *
1#
#182000
0#
b111000 "
b111000 '
#183000
b11110 *
1#
#184000
0#
b111001 "
b111001 '
#185000
b11111 *
1#
#186000
0#
#187000
b0 *
1#
#188000
0#
b111000 "
b111000 '
#189000
1#
#190000
0#
b100011 "
b100011 '
#191000
1#
#192000
0#
b1011110 "
b1011110 '
#193000
b1 *
1#
#194000
0#
b110010 "
b110010 '
#195000
b10 *
1#
#196000
0#
b110100 "
b110100 '
#197000
b11 *
1#
#198000
0#
b110010 "
b110010 '
#199000
b100 *
1#
#200000
0#
b1000000 "
b1000000 '
#201000
b110 *
1#
#202000
0#
b110000 "
b110000 '
#203000
b111 *
1#
#204000
0#
#205000
b1000 *
1#
#206000
0#
#207000
b1001 *
1#
#208000
0#
#209000
b1010 *
1#
#210000
0#
b110011 "
b110011 '
#211000
b1011 *
1#
#212000
0#
b110000 "
b110000 '
#213000
b1100 *
1#
#214000
0#
b1100110 "
b1100110 '
#215000
b1101 *
1#
#216000
0#
b110100 "
b110100 '
#217000
b1110 *
1#
#218000
0#
b111010 "
b111010 '
#219000
b1111 *
1#
#220000
0#
b100000 "
b100000 '
#221000
1#
#222000
0#
b100100 "
b100100 '
#223000
b10000 *
1#
#224000
0#
b110011 "
b110011 '
#225000
b10001 *
1#
#226000
0#
b110001 "
b110001 '
#227000
b10010 *
1#
#228000
0#
b100000 "
b100000 '
#229000
b10101 *
1#
#230000
0#
b111100 "
b111100 '
#231000
b10110 *
1#
#232000
0#
b111101 "
b111101 '
#233000
b10111 *
1#
#234000
0#
b100011 "
b100011 '
#235000
b0 *
1#
#236000
0#
b1011110 "
b1011110 '
#237000
b1 *
1#
#238000
0#
b110010 "
b110010 '
#239000
b10 *
1#
#240000
0#
b110100 "
b110100 '
#241000
b11 *
1#
#242000
0#
b110010 "
b110010 '
#243000
b100 *
1#
#244000
0#
b1000000 "
b1000000 '
#245000
b110 *
1#
#246000
0#
b110000 "
b110000 '
#247000
b111 *
1#
#248000
0#
#249000
b1000 *
1#
#250000
0#
#251000
b1001 *
1#
#252000
0#
#253000
b1010 *
1#
#254000
0#
b110011 "
b110011 '
#255000
b1011 *
1#
#256000
0#
b110000 "
b110000 '
#257000
b1100 *
1#
#258000
0#
b1100110 "
b1100110 '
#259000
b1101 *
1#
#260000
0#
b110100 "
b110100 '
#261000
b1110 *
1#
#262000
0#
b111010 "
b111010 '
#263000
b1111 *
1#
#264000
0#
b100000 "
b100000 '
#265000
1#
#266000
0#
b100100 "
b100100 '
#267000
b10000 *
1#
#268000
0#
b110011 "
b110011 '
#269000
b10001 *
1#
#270000
0#
b110001 "
b110001 '
#271000
b10010 *
1#
#272000
0#
b100000 "
b100000 '
#273000
b10101 *
1#
#274000
0#
b111100 "
b111100 '
#275000
b10110 *
1#
#276000
0#
b111101 "
b111101 '
#277000
b10111 *
1#
#278000
0#
b100000 "
b100000 '
#279000
1#
#280000
0#
#281000
1#
#282000
0#
#283000
1#
#284000
0#
b110001 "
b110001 '
#285000
b11000 *
1#
#286000
0#
b110010 "
b110010 '
#287000
b11001 *
1#
#288000
0#
b110011 "
b110011 '
#289000
b11010 *
1#
#290000
0#
b110010 "
b110010 '
#291000
b11011 *
1#
#292000
0#
b110001 "
b110001 '
#293000
b11100 *
1#
#294000
0#
b110101 "
b110101 '
#295000
b11101 *
1#
#296000
0#
b100000 "
b100000 '
#297000
b0 *
1#
#298000
0#
b100011 "
b100011 '
#299000
1#
#300000
0#
b1011110 "
b1011110 '
#301000
b1 *
1#
#302000
0#
b110010 "
b110010 '
#303000
b10 *
1#
#304000
0#
b110100 "
b110100 '
#305000
b11 *
1#
#306000
0#
b110010 "
b110010 '
#307000
b100 *
1#
#308000
0#
b1000000 "
b1000000 '
#309000
b110 *
1#
#310000
0#
b110000 "
b110000 '
#311000
b111 *
1#
#312000
0#
#313000
b1000 *
1#
#314000
0#
#315000
b1001 *
1#
#316000
0#
#317000
b1010 *
1#
#318000
0#
b110011 "
b110011 '
#319000
b1011 *
1#
#320000
0#
b110000 "
b110000 '
#321000
b1100 *
1#
#322000
0#
b1100110 "
b1100110 '
#323000
b1101 *
1#
#324000
0#
b110100 "
b110100 '
#325000
b1110 *
1#
#326000
0#
b111010 "
b111010 '
#327000
b1111 *
1#
#328000
0#
b100000 "
b100000 '
#329000
1#
#330000
0#
b100100 "
b100100 '
#331000
b10000 *
1#
#332000
0#
b110011 "
b110011 '
#333000
b10001 *
1#
#334000
0#
b110001 "
b110001 '
#335000
b10010 *
1#
#336000
0#
b100000 "
b100000 '
#337000
b10101 *
1#
#338000
0#
b111100 "
b111100 '
#339000
b10110 *
1#
#340000
0#
b111101 "
b111101 '
#341000
b10111 *
1#
#342000
0#
b100000 "
b100000 '
#343000
1#
#344000
0#
#345000
1#
