p1/FloatType/VoterPlus.v
module VoterPlus(
	input clk,
	input reset,
	input [31:0] np,
	input [7:0] vip,
	input vvip,
	output reg [7:0] result
);
reg [31:0] np_state;
reg [7:0] vip_state;
reg vvip_state;
integer count = 0,i;
always @(posedge clk,posedge reset) begin
	if(reset == 1) begin
	  np_state <= 0;
	  vip_state <= 0;
	  vvip_state <= 0;
	  count <= 0;
	  result <= 0;
	end
	else begin
	  for(i = 0;i < 32;i = i + 1) begin
		if(np[i] == 1 && np_state[i] == 0) begin
		  np_state[i] = 1;
		  count = count + 1;
		end
	  end
	  for(i = 0;i < 8;i = i + 1) begin
		if(vip[i] == 1 && vip_state[i] == 0) begin
		  vip_state[i] = 1;
		  count = count + 4;
		end
	  end
	  if(vvip == 1 && vvip_state == 0) begin
		vvip_state = 1;
		count = count + 16;
	  end
	  result <= count;
	end
end

endmodule

p1/FloatType/test_tb.v
`timescale  1ns / 1ps
`include "VoterPlus.v"
module tb_VoterPlus;

// VoterPlus Parameters
parameter PERIOD  = 10;


// VoterPlus Inputs
reg   clk                                  = 0 ;
reg   reset                                = 0 ;
reg   [31:0]  np                           = 0 ;
reg   [7:0]  vip                           = 0 ;
reg   vvip                                 = 0 ;

// VoterPlus Outputs
wire  [7:0]  result                        ;


VoterPlus  u_VoterPlus (
    .clk                     ( clk            ),
    .reset                   ( reset          ),
    .np                      ( np      [31:0] ),
    .vip                     ( vip     [7:0]  ),
    .vvip                    ( vvip           ),

    .result                  ( result  [7:0]  )
);
always #5 clk = ~clk;
initial
begin
    $dumpfile("test.vcd");
    $dumpvars;
    reset = 1;
    #2
    reset = 0;
    np = 32'hfffffff0;
    vip = 8'b1101_0101;
    vvip = 0;
    #3;
    #5;
    np = 32'h000f;
    vip = 8'b0010_1010;
    vvip = 1;
    #100;
    $finish;
end

endmodule

p1/FloatType/test.vcd
$date
	Mon Oct 10 11:15:29 2022
$end
$version
	Icarus Verilog
$end
$timescale
	1ps
$end
$scope module tb_VoterPlus $end
$var wire 8 ! result [7:0] $end
$var reg 1 " clk $end
$var reg 32 # np [31:0] $end
$var reg 1 $ reset $end
$var reg 8 % vip [7:0] $end
$var reg 1 & vvip $end
$scope module u_VoterPlus $end
$var wire 1 " clk $end
$var wire 32 ' np [31:0] $end
$var wire 1 $ reset $end
$var wire 8 ( vip [7:0] $end
$var wire 1 & vvip $end
$var reg 32 ) np_state [31:0] $end
$var reg 8 * result [7:0] $end
$var reg 8 + vip_state [7:0] $end
$var reg 1 , vvip_state $end
$var integer 32 - count [31:0] $end
$var integer 32 . i [31:0] $end
$upscope $end
$upscope $end
$enddefinitions $end
#0
$dumpvars
bx .
b0 -
0,
b0 +
b0 *
b0 )
b0 (
b0 '
0&
b0 %
1$
b0 #
0"
b0 !
$end
#2000
b11010101 %
b11010101 (
b11111111111111111111111111110000 #
b11111111111111111111111111110000 '
0$
#5000
b110000 !
b110000 *
b11010101 +
b110000 -
b11111111111111111111111111110000 )
b1000 .
1"
#10000
1&
b101010 %
b101010 (
b1111 #
b1111 '
0"
#15000
b1010000 !
b1010000 *
1,
b11111111 +
b1010000 -
b11111111111111111111111111111111 )
b1000 .
1"
#20000
0"
#25000
b1000 .
1"
#30000
0"
#35000
b1000 .
1"
#40000
0"
#45000
b1000 .
1"
#50000
0"
#55000
b1000 .
1"
#60000
0"
#65000
b1000 .
1"
#70000
0"
#75000
b1000 .
1"
#80000
0"
#85000
b1000 .
1"
#90000
0"
#95000
b1000 .
1"
#100000
0"
#105000
b1000 .
1"
