Pre/Pre_Verilog/IDfsm/id_fsm.v
module id_fsm(
    input [7:0] char,
    input clk,
    output reg out
);
reg [7:0] id[1023:0];
integer i = 0;                                        
integer j;
always @(posedge clk) begin
      id[i] <= char;
      if(out == 1'b1) begin
        if(char >= "0" && char <= "9") 
            out <= 1'b1;
        else
            out <= 1'b0;
      end
      else begin
        if(char >= "0" && char <= "9") begin
            for(j = i - 1;j != -1 && id[j]>= "0" && id[j] <= "9";j = j - 1);
            if(j == -1)
                out <= 1'b0;
            else if((id[j] >= "a" && id[j] <="z")||(id[j] >= "A" && id[j] <="Z"))
                out <= 1'b1;
            else
                out <= 1'b0;
        end
        else
            out <= 1'b0;
      end
    i = i + 1;
end
endmodule

Pre/Pre_Verilog/IDfsm/id_fsm_tb.v
`timescale  1ns / 1ps
`include "id_fsm.v"
module tb_id_fsm;

// id_fsm Parameters
parameter PERIOD  = 10;


// id_fsm Inputs
reg   [7:0]  char                          = 0 ;
reg   clk                                  = 0 ;

// id_fsm Outputs
wire  out                                  ;


id_fsm  u_id_fsm (
    .char                    ( char  [7:0] ),
    .clk                     ( clk         ),

    .out                     ( out         )
);
always #5 clk = ~clk;
initial
begin
    $dumpfile("id_fsm.vcd");
    $dumpvars;
    #10
    char = "1";//a
    #10
    char = "2";//b
    #10
    char = 99;//c
    #10
    char = 100;//d
    #10
    char = 49;//1
    #10
    char = 50;//2
    #10
    char = 51;//3
    #10
    char = 58;//:
    #10
    $finish;
end

endmodule

Pre/Pre_Verilog/IDfsm/id_fsm.vcd
$date
	Wed Sep 07 21:39:11 2022
$end
$version
	Icarus Verilog
$end
$timescale
	1ps
$end
$scope module tb_id_fsm $end
$var wire 1 ! out $end
$var reg 8 " char [7:0] $end
$var reg 1 # clk $end
$scope module u_id_fsm $end
$var wire 8 $ char [7:0] $end
$var wire 1 # clk $end
$var reg 1 ! out $end
$var integer 32 % i [31:0] $end
$var integer 32 & j [31:0] $end
$upscope $end
$upscope $end
$enddefinitions $end
#0
$dumpvars
bx &
b0 %
b0 $
0#
b0 "
x!
$end
#5000
0!
b1 %
1#
#10000
0#
b110001 "
b110001 $
#15000
b10 %
b0 &
1#
#20000
0#
b110010 "
b110010 $
#25000
b11 %
b0 &
1#
#30000
0#
b1100011 "
b1100011 $
#35000
b100 %
1#
#40000
0#
b1100100 "
b1100100 $
#45000
b101 %
1#
#50000
0#
b110001 "
b110001 $
#55000
1!
b110 %
b100 &
1#
#60000
0#
b110010 "
b110010 $
#65000
b111 %
1#
#70000
0#
b110011 "
b110011 $
#75000
b1000 %
1#
#80000
0#
b111010 "
b111010 $
#85000
0!
b1001 %
1#
